taser/__init__.py
taser/dns.py
taser/ftp.py
taser/logx.py
taser/smtp.py
taser/tcp.py
taser/utils.py
taser/http/__init__.py
taser/http/browser.py
taser/http/parser.py
taser/http/spider.py
taser/resources/__init__.py
taser/resources/user_agents.py
taser-0.4.4.dist-info/LICENSE
taser-0.4.4.dist-info/METADATA
taser-0.4.4.dist-info/WHEEL
taser-0.4.4.dist-info/top_level.txt
taser-0.4.4.dist-info/RECORD
