Metadata-Version: 2.1
Name: taser
Version: 0.4.4
Summary: Security Resource library
Home-page: https://github.com/m8sec/taser
Author: m8sec
License: BSD 3-clause
Classifier: Programming Language :: Python :: 3
Classifier: Intended Audience :: Developers
Classifier: License :: OSI Approved :: BSD License
License-File: LICENSE
Requires-Dist: beautifulsoup4
Requires-Dist: bs4
Requires-Dist: cryptography
Requires-Dist: dnspython
Requires-Dist: ipparser >=1.0.0
Requires-Dist: lxml
Requires-Dist: ntlm-auth
Requires-Dist: requests
Requires-Dist: requests-file
Requires-Dist: requests-ntlm
Requires-Dist: tldextract
Requires-Dist: selenium
Requires-Dist: selenium-wire
Requires-Dist: webdriver-manager
